tv_extract/__init__.py
tv_extract/_version.py
tv_extract/extract.py
tv_extract/git_extract.py
tv_extract/data/__init__.py
tv_extract/data/config.py
tv_extract/data/extract.py
tv_extract/data/file_info.py
tv_extract/data/pr.py
tv_extract/data/repo.py
tv_extract/data/revision.py
tv_extract/data/revision_graph.py
tv_extract/gitextractor/__init__.py
tv_extract/gitextractor/extract_complete_file_info.py
tv_extract/gitextractor/extract_pr_data.py
tv_extract/gitextractor/extract_revision_graph.py
tv_extract/gitextractor/loc_cache.py
tv_extract/util/__init__.py
tv_extract/util/cd.py
tv_extract/util/cli.py
tv_extract/util/shell_cmds.py
tv_extract-1.0.15.dist-info/LICENSE
tv_extract-1.0.15.dist-info/METADATA
tv_extract-1.0.15.dist-info/WHEEL
tv_extract-1.0.15.dist-info/entry_points.txt
tv_extract-1.0.15.dist-info/top_level.txt
tv_extract-1.0.15.dist-info/RECORD
