Metadata-Version: 2.1
Name: tv-extract
Version: 1.0.15
Summary: Team Viewer - Data Extract for analysis
Home-page: https://github.com/rappdw/tv-extract
Author: rappdw
Author-email: rappdw@gmail.com
License: MIT
Keywords: library
Platform: UNKNOWN
Classifier: Development Status :: 5 - Production/Stable
Classifier: Intended Audience :: Developers
Classifier: Topic :: Scientific/Engineering :: Visualization
Classifier: Topic :: Software Development :: Version Control :: Git
Classifier: Topic :: Software Development :: Libraries :: Python Modules
Classifier: License :: OSI Approved :: MIT License
Classifier: Programming Language :: Python :: 3.6
Classifier: Programming Language :: Python :: 3.7
Requires-Dist: gitpython
Requires-Dist: multiprocessing-logging
Requires-Dist: ordered-set
Requires-Dist: dataclasses ; python_version < "3.7"
Provides-Extra: dev
Requires-Dist: wheel (>=0.30.0) ; extra == 'dev'
Requires-Dist: twine ; extra == 'dev'
Provides-Extra: test
Requires-Dist: pytest ; extra == 'test'
Requires-Dist: pytest-cov ; extra == 'test'
